Perceptron/__init__.py
Perceptron/perceptron.py
Perceptron_pkg_Rushi9867-0.0.1.dist-info/LICENSE
Perceptron_pkg_Rushi9867-0.0.1.dist-info/METADATA
Perceptron_pkg_Rushi9867-0.0.1.dist-info/WHEEL
Perceptron_pkg_Rushi9867-0.0.1.dist-info/top_level.txt
Perceptron_pkg_Rushi9867-0.0.1.dist-info/RECORD
