Metadata-Version: 2.1
Name: Perceptron-pkg-Rushi9867
Version: 0.0.1
Summary: A small package for perceptron
Home-page: https://github.com/Rushi9867/PerceptronPKG
Author: Rushi9867
Author-email: rushikhandare2203@gmail.com
Project-URL: Bug Tracker, https://github.com/Rushi9867/PerceptronPKG/issues
Classifier: Programming Language :: Python :: 3
Classifier: License :: OSI Approved :: MIT License
Classifier: Operating System :: OS Independent
Requires-Python: >=3.6
License-File: LICENSE
Requires-Dist: numpy (==1.22.3)
Requires-Dist: pandas (==1.4.2)
Requires-Dist: joblib (==1.2.0)
